fwl_proteus-25.10.15.dist-info/licenses/LICENSE.txt
proteus/__init__.py
proteus/cli.py
proteus/doctor.py
proteus/proteus.py
proteus/atmos_chem/__init__.py
proteus/atmos_chem/common.py
proteus/atmos_chem/vulcan.py
proteus/atmos_chem/wrapper.py
proteus/atmos_clim/__init__.py
proteus/atmos_clim/agni.py
proteus/atmos_clim/common.py
proteus/atmos_clim/dummy.py
proteus/atmos_clim/janus.py
proteus/atmos_clim/wrapper.py
proteus/config/__init__.py
proteus/config/_atmos_chem.py
proteus/config/_atmos_clim.py
proteus/config/_config.py
proteus/config/_converters.py
proteus/config/_delivery.py
proteus/config/_escape.py
proteus/config/_interior.py
proteus/config/_observe.py
proteus/config/_orbit.py
proteus/config/_outgas.py
proteus/config/_params.py
proteus/config/_star.py
proteus/config/_struct.py
proteus/escape/wrapper.py
proteus/grid/manage.py
proteus/inference/BO.py
proteus/inference/async_BO.py
proteus/inference/gen_D_init.py
proteus/inference/inference.py
proteus/inference/objective.py
proteus/inference/plot.py
proteus/inference/test.py
proteus/inference/utils.py
proteus/interior/__init__.py
proteus/interior/aragog.py
proteus/interior/common.py
proteus/interior/dummy.py
proteus/interior/spider.py
proteus/interior/timestep.py
proteus/interior/wrapper.py
proteus/interior/zalmoxis.py
proteus/observe/__init__.py
proteus/observe/common.py
proteus/observe/platon.py
proteus/observe/wrapper.py
proteus/orbit/__init__.py
proteus/orbit/dummy.py
proteus/orbit/lovepy.py
proteus/orbit/orbit.py
proteus/orbit/satellite.py
proteus/orbit/wrapper.py
proteus/outgas/__init__.py
proteus/outgas/calliope.py
proteus/outgas/common.py
proteus/outgas/wrapper.py
proteus/plot/__init__.py
proteus/plot/_cpl_helpers.py
proteus/plot/cpl_atmosphere.py
proteus/plot/cpl_atmosphere_cbar.py
proteus/plot/cpl_bolometry.py
proteus/plot/cpl_chem_atmosphere.py
proteus/plot/cpl_emission.py
proteus/plot/cpl_escape.py
proteus/plot/cpl_fluxes_atmosphere.py
proteus/plot/cpl_fluxes_global.py
proteus/plot/cpl_global.py
proteus/plot/cpl_interior.py
fwl_proteus-25.10.15.dist-info/METADATA
fwl_proteus-25.10.15.dist-info/WHEEL
fwl_proteus-25.10.15.dist-info/entry_points.txt
fwl_proteus-25.10.15.dist-info/top_level.txt
fwl_proteus-25.10.15.dist-info/RECORD
