Metadata-Version: 2.4
Name: fwl-proteus
Version: 25.10.15
Summary: Coupled atmosphere-interior framework to simulate the temporal evolution of rocky planets
Author-email: Tim Lichtenberg <tim.lichtenberg@rug.nl>, Harrison Nicholls <harrison.nicholls@physics.ox.ac.uk>, Laurent Soucasse <l.soucasse@esciencecenter.nl>, Mariana Sastre <m.c.villamil.sastre@rug.nl>, Emma Postolec <e.n.postolec@rug.nl>, Flavia Pascal <fpascal@astro.rug.nl>, Ben Riegler <ben.riegler@tum.de>, Hanno Spreeuw <h.spreeuw@esciencecenter.nl>, "Dan J. Bower" <dbower@ethz.ch>, Mark Hammond <mark.hammond@physics.ox.ac.uk>, Stef Smeets <s.smeets@esciencecenter.nl>, Robb Calder <rdc49@
License: Apache 2.0 License
Project-URL: homepage, https://github.com/FormingWorlds/PROTEUS
Project-URL: issues, https://github.com/FormingWorlds/PROTEUS/issues
Project-URL: documentation, https://fwl-proteus.readthedocs.io
Project-URL: changelog, https://github.com/FormingWorlds/PROTEUS/releases
Keywords: Astronomy,Exoplanets,Model-coupling
Classifier: Development Status :: 3 - Alpha
Classifier: Intended Audience :: Science/Research
Classifier: License :: OSI Approved :: Apache Software License
Classifier: Natural Language :: English
Classifier: Operating System :: OS Independent
Classifier: Programming Language :: Python :: 3
Classifier: Programming Language :: Python :: 3.11
Classifier: Programming Language :: Python :: 3.12
Classifier: Programming Language :: Python :: 3.13
Classifier: Topic :: Scientific/Engineering :: Astronomy
Requires-Python: >=3.11
License-File: LICENSE.txt
Requires-Dist: attrs
Requires-Dist: cattrs
Requires-Dist: fwl-janus>=24.11.05
Requires-Dist: fwl-mors>=25.07.15
Requires-Dist: fwl-calliope>=25.05.01
Requires-Dist: fwl-zephyrus>=25.03.11
Requires-Dist: aragog>=v0.2.8-alpha
Requires-Dist: fwl-zalmoxis>=25.09.07
Requires-Dist: cmcrameri
Requires-Dist: juliacall
Requires-Dist: matplotlib
Requires-Dist: netCDF4
Requires-Dist: numpy>=2.0.0
Requires-Dist: pandas
Requires-Dist: scipy
Requires-Dist: pre-commit
Requires-Dist: platformdirs
Requires-Dist: ruff
Requires-Dist: sympy
Requires-Dist: astropy
Requires-Dist: torch
Requires-Dist: botorch
Requires-Dist: gpytorch
Requires-Dist: toml
Requires-Dist: zenodo-get
Provides-Extra: develop
Requires-Dist: bump-my-version; extra == "develop"
Requires-Dist: coverage[toml]; extra == "develop"
Requires-Dist: pillow; extra == "develop"
Requires-Dist: pip-tools; extra == "develop"
Requires-Dist: pytest>=8.1; extra == "develop"
Requires-Dist: pytest-dependency; extra == "develop"
Provides-Extra: docs
Requires-Dist: markdown-include; extra == "docs"
Requires-Dist: mkdocs; extra == "docs"
Requires-Dist: mkdocs-material; extra == "docs"
Requires-Dist: mkdocstrings[python]; extra == "docs"
Dynamic: license-file
